MANIFEST.in
README.rst
setup.py
datatype/__init__.py
datatype/coercion.py
datatype/decorators.py
datatype/tools.py
datatype/validation.py
datatype.egg-info/PKG-INFO
datatype.egg-info/SOURCES.txt
datatype.egg-info/dependency_links.txt
datatype.egg-info/requires.txt
datatype.egg-info/top_level.txt