Metadata-Version: 1.0
Name: datatype
Version: 0.8.0
Summary: Anonymous datatype validation
Home-page: https://github.com/LearningStation/datatype
Author: Adam Wagner
Author-email: awagner83@gmail.com
License: BSD3
Platform: UNKNOWN
Classifier: Development Status :: 4 - Beta
Classifier: Topic :: Software Development
Classifier: Intended Audience :: Developers
Classifier: Programming Language :: Python
Classifier: Topic :: Software Development :: Quality Assurance
Classifier: Topic :: Software Development :: Libraries
